diggs/__init__.py
diggs/cli.py
diggs/diggs.py
diggs-0.0.5.dist-info/AUTHORS.rst
diggs-0.0.5.dist-info/LICENSE
diggs-0.0.5.dist-info/METADATA
diggs-0.0.5.dist-info/WHEEL
diggs-0.0.5.dist-info/entry_points.txt
diggs-0.0.5.dist-info/top_level.txt
diggs-0.0.5.dist-info/RECORD
