Metadata-Version: 2.1
Name: diggs
Version: 0.0.5
Summary: A Python package for Data Interchange for Geotechnical and Geoenvironmental Specialists (DIGGS).
Home-page: https://github.com/xinp-hub/diggs
Author: Xin Peng
Author-email: xin_peng@outlook.com
License: GNU General Public License v3
Keywords: diggs
Platform: UNKNOWN
Classifier: Development Status :: 2 - Pre-Alpha
Classifier: Intended Audience :: Developers
Classifier: License :: OSI Approved :: GNU General Public License v3 (GPLv3)
Classifier: Natural Language :: English
Classifier: Programming Language :: Python :: 3
Classifier: Programming Language :: Python :: 3.6
Classifier: Programming Language :: Python :: 3.7
Classifier: Programming Language :: Python :: 3.8
Requires-Python: >=3.6
License-File: LICENSE
License-File: AUTHORS.rst
